LICENSE
README.md
markdown_mark.py
setup.py
markdown_mark.egg-info/PKG-INFO
markdown_mark.egg-info/SOURCES.txt
markdown_mark.egg-info/dependency_links.txt
markdown_mark.egg-info/requires.txt
markdown_mark.egg-info/top_level.txt